dec2bin/dec2bin.vhdl
-- Copyright (c) 2019 Patrick Pedersen

-- Permission is hereby granted, free of charge, to any person obtaining a copy
-- of this software and associated documentation files (the "Software"), to deal
-- in the Software without restriction, including without limitation the rights
-- to use, copy, modify, merge, publish, distribute, sublicense, and/or sell
-- copies of the Software, and to permit persons to whom the Software is
-- furnished to do so, subject to the following conditions:

-- The above copyright notice and this permission notice shall be included in all
-- copies or substantial portions of the Software.

-- THE SOFTWARE IS PROVIDED "AS IS", WITHOUT WARRANTY OF ANY KIND, EXPRESS OR
-- IMPLIED, INCLUDING BUT NOT LIMITED TO THE WARRANTIES OF MERCHANTABILITY,
-- FITNESS FOR A PARTICULAR PURPOSE AND NONINFRINGEMENT. IN NO EVENT SHALL THE
-- AUTHORS OR COPYRIGHT HOLDERS BE LIABLE FOR ANY CLAIM, DAMAGES OR OTHER
-- LIABILITY, WHETHER IN AN ACTION OF CONTRACT, TORT OR OTHERWISE, ARISING FROM,
-- OUT OF OR IN CONNECTION WITH THE SOFTWARE OR THE USE OR OTHER DEALINGS IN THE
-- SOFTWARE.

-- Author       : Patrick Pedersen
-- Description  : A simple decimal to binary encoder

library ieee;
use ieee.std_logic_1164.all;
use ieee.numeric_std.all;

entity dec2bin is
    port
    (
        dec : in std_logic_vector(9 downto 0);
        bin : out std_logic_vector(3 downto 0)
    );
end entity;

architecture dec2bin_arch of dec2bin is
begin
    process (dec)
    begin
        -- Find HIGH dec input, then convert to binary
        for i in 0 to dec'length - 1 loop
            if dec(i) = '1' then
                bin <= std_logic_vector(to_unsigned(i, bin'length));
            end if;
        end loop;
    end process;
end architecture;

dec2bin/dec2bin_tb.vhdl
-- Copyright (c) 2019 Patrick Pedersen

-- Permission is hereby granted, free of charge, to any person obtaining a copy
-- of this software and associated documentation files (the "Software"), to deal
-- in the Software without restriction, including without limitation the rights
-- to use, copy, modify, merge, publish, distribute, sublicense, and/or sell
-- copies of the Software, and to permit persons to whom the Software is
-- furnished to do so, subject to the following conditions:

-- The above copyright notice and this permission notice shall be included in all
-- copies or substantial portions of the Software.

-- THE SOFTWARE IS PROVIDED "AS IS", WITHOUT WARRANTY OF ANY KIND, EXPRESS OR
-- IMPLIED, INCLUDING BUT NOT LIMITED TO THE WARRANTIES OF MERCHANTABILITY,
-- FITNESS FOR A PARTICULAR PURPOSE AND NONINFRINGEMENT. IN NO EVENT SHALL THE
-- AUTHORS OR COPYRIGHT HOLDERS BE LIABLE FOR ANY CLAIM, DAMAGES OR OTHER
-- LIABILITY, WHETHER IN AN ACTION OF CONTRACT, TORT OR OTHERWISE, ARISING FROM,
-- OUT OF OR IN CONNECTION WITH THE SOFTWARE OR THE USE OR OTHER DEALINGS IN THE
-- SOFTWARE.

-- Author       : Patrick Pedersen
-- Description  : Test bench for the decimal to binary encoder

library ieee;
use ieee.std_logic_1164.all;
use ieee.numeric_std.all;

entity dec2bin_tb is
end entity;

architecture dec2bin_tb_arch of dec2bin_tb is

    signal dec_tb : std_logic_vector(9 downto 0);
    signal bin_tb : std_logic_vector(3 downto 0);

begin
    
    DEC2BIN_INST : entity work.dec2bin(dec2bin_arch)
    port map (dec_tb, bin_tb);

    process
        variable err : boolean := false;
    begin
        -- Find HIGH dec input, then convert to binary
        for i in 0 to dec_tb'length - 1 loop
            dec_tb <= (others => '0');
            dec_tb(i) <= '1';
            
            wait for 5 ns;

            if bin_tb /= std_logic_vector(to_unsigned(i, bin_tb'length)) then
                report "The decimal to binary decoder does not generate correct output!" severity error;
                err := true;
            end if;
        
        end loop;

        if err then
            report "The decimal to binary decoder does not function properly!" severity failure;
        end if;

        report "The decimal to binary decoder functions properly!";
        
        wait;
    end process;
end architecture;

dec2bin/dec2bin_tb.vcd
$date
  Wed Dec 18 14:31:39 2019
$end
$version
  GHDL v0
$end
$timescale
  1 fs
$end
$scope module standard $end
$upscope $end
$scope module std_logic_1164 $end
$upscope $end
$scope module numeric_std $end
$upscope $end
$scope module dec2bin_tb $end
$var reg 10 ! dec_tb[9:0] $end
$var reg 4 " bin_tb[3:0] $end
$scope module dec2bin_inst $end
$var reg 10 # dec[9:0] $end
$var reg 4 $ bin[3:0] $end
$upscope $end
$upscope $end
$enddefinitions $end
#0
b0000000001 !
b0000 "
b0000000001 #
b0000 $
#5000000
b0000000010 !
b0001 "
b0000000010 #
b0001 $
#10000000
b0000000100 !
b0010 "
b0000000100 #
b0010 $
#15000000
b0000001000 !
b0011 "
b0000001000 #
b0011 $
#20000000
b0000010000 !
b0100 "
b0000010000 #
b0100 $
#25000000
b0000100000 !
b0101 "
b0000100000 #
b0101 $
#30000000
b0001000000 !
b0110 "
b0001000000 #
b0110 $
#35000000
b0010000000 !
b0111 "
b0010000000 #
b0111 $
#40000000
b0100000000 !
b1000 "
b0100000000 #
b1000 $
#45000000
b1000000000 !
b1001 "
b1000000000 #
b1001 $
